llamamlx_embeddings/__init__.py
llamamlx_embeddings/cli.py
llamamlx_embeddings/client.py
llamamlx_embeddings/logging.py
llamamlx_embeddings/version.py
llamamlx_embeddings/api/__init__.py
llamamlx_embeddings/api/main.py
llamamlx_embeddings/benchmarks/__init__.py
llamamlx_embeddings/benchmarks/benchmark.py
llamamlx_embeddings/benchmarks/run_benchmarks.py
llamamlx_embeddings/benchmarks/utils.py
llamamlx_embeddings/benchmarks/visualization.py
llamamlx_embeddings/conversion/__init__.py
llamamlx_embeddings/conversion/convert.py
llamamlx_embeddings/core/__init__.py
llamamlx_embeddings/core/conversion.py
llamamlx_embeddings/core/embeddings.py
llamamlx_embeddings/core/mock_embeddings.py
llamamlx_embeddings/core/models.py
llamamlx_embeddings/core/onnx_embedding.py
llamamlx_embeddings/core/quantization.py
llamamlx_embeddings/core/sparse.py
llamamlx_embeddings/core/mlx_models/__init__.py
llamamlx_embeddings/core/mlx_models/bert.py
llamamlx_embeddings/core/mlx_models/models/__init__.py
llamamlx_embeddings/core/mlx_models/models/base.py
llamamlx_embeddings/core/mlx_models/models/bert.py
llamamlx_embeddings/integrations/__init__.py
llamamlx_embeddings/integrations/base.py
llamamlx_embeddings/integrations/pinecone.py
llamamlx_embeddings/integrations/qdrant.py
llamamlx_embeddings/processing/__init__.py
llamamlx_embeddings/processing/text.py
llamamlx_embeddings/quantization/__init__.py
llamamlx_embeddings/quantization/quantize.py
llamamlx_embeddings/utils/__init__.py
llamamlx_embeddings/utils/error_handling.py
llamamlx_embeddings/visualization/__init__.py
llamamlx_embeddings/visualization/charts.py
llamamlx_embeddings_llamasearch-0.2.0.dist-info/licenses/LICENSE
llamamlx_embeddings_llamasearch-0.2.0.dist-info/METADATA
llamamlx_embeddings_llamasearch-0.2.0.dist-info/WHEEL
llamamlx_embeddings_llamasearch-0.2.0.dist-info/entry_points.txt
llamamlx_embeddings_llamasearch-0.2.0.dist-info/top_level.txt
llamamlx_embeddings_llamasearch-0.2.0.dist-info/RECORD
