Metadata-Version: 2.4
Name: llamamlx-embeddings-llamasearch
Version: 0.2.0
Summary: Fast and efficient text embeddings using MLX on Apple Silicon
Home-page: https://llamasearch.ai
Author: LlamaSearch AI
Author-email: nikjois@llamasearch.ai
Project-URL: Bug Tracker, https://github.com/yourusername/llamamlx-embeddings/issues
Classifier: Programming Language :: Python :: 3
Classifier: License :: OSI Approved :: MIT License
Classifier: Operating System :: MacOS
Classifier: Development Status :: 4 - Beta
Classifier: Intended Audience :: Developers
Classifier: Intended Audience :: Science/Research
Classifier: Topic :: Scientific/Engineering :: Artificial Intelligence
Requires-Python: >=3.8
License-File: LICENSE
Requires-Dist: mlx>=0.2.0
Requires-Dist: numpy>=1.20.0
Requires-Dist: transformers>=4.30.0
Requires-Dist: huggingface-hub>=0.15.0
Requires-Dist: torch>=2.0.0
Requires-Dist: fastapi>=0.100.0
Requires-Dist: uvicorn>=0.22.0
Requires-Dist: pydantic>=2.0.0
Provides-Extra: dev
Requires-Dist: pytest>=7.0.0; extra == "dev"
Requires-Dist: black>=23.0.0; extra == "dev"
Requires-Dist: isort>=5.12.0; extra == "dev"
Requires-Dist: mypy>=1.0.0; extra == "dev"
Requires-Dist: flake8>=6.0.0; extra == "dev"
Provides-Extra: onnx
Requires-Dist: onnxruntime>=1.15.0; extra == "onnx"
Provides-Extra: pinecone
Requires-Dist: pinecone>=3.0.0; extra == "pinecone"
Provides-Extra: qdrant
Requires-Dist: qdrant-client>=1.5.0; extra == "qdrant"
Provides-Extra: visualization
Requires-Dist: matplotlib>=3.6.0; extra == "visualization"
Requires-Dist: seaborn>=0.12.0; extra == "visualization"
Requires-Dist: scikit-learn>=1.2.0; extra == "visualization"
Provides-Extra: docs
Requires-Dist: sphinx>=6.0.0; extra == "docs"
Requires-Dist: sphinx-rtd-theme>=1.2.0; extra == "docs"
Requires-Dist: myst-parser>=2.0.0; extra == "docs"
Provides-Extra: all
Requires-Dist: onnxruntime>=1.15.0; extra == "all"
Requires-Dist: pinecone>=3.0.0; extra == "all"
Requires-Dist: qdrant-client>=1.5.0; extra == "all"
Requires-Dist: matplotlib>=3.6.0; extra == "all"
Requires-Dist: seaborn>=0.12.0; extra == "all"
Requires-Dist: scikit-learn>=1.2.0; extra == "all"
Requires-Dist: nltk>=3.8.0; extra == "all"
Dynamic: author
Dynamic: author-email
Dynamic: classifier
Dynamic: description
Dynamic: description-content-type
Dynamic: home-page
Dynamic: license-file
Dynamic: project-url
Dynamic: provides-extra
Dynamic: requires-dist
Dynamic: requires-python
Dynamic: summary
